markov_random_field/__init__.py
markov_random_field/markov_random_field.py
markov_random_field-0.1.1.dist-info/LICENSE
markov_random_field-0.1.1.dist-info/METADATA
markov_random_field-0.1.1.dist-info/WHEEL
markov_random_field-0.1.1.dist-info/top_level.txt
markov_random_field-0.1.1.dist-info/RECORD
